django_knowledge_share-0.1.2.dist-info/DESCRIPTION.rst
django_knowledge_share-0.1.2.dist-info/METADATA
django_knowledge_share-0.1.2.dist-info/RECORD
django_knowledge_share-0.1.2.dist-info/WHEEL
django_knowledge_share-0.1.2.dist-info/metadata.json
django_knowledge_share-0.1.2.dist-info/top_level.txt
knowledge_share/__init__.py
knowledge_share/apps.py
knowledge_share/conf.py
knowledge_share/exceptions.py
knowledge_share/models.py
knowledge_share/rss_feeds.py
knowledge_share/twitter_helpers.py
knowledge_share/urls.py
knowledge_share/views.py
knowledge_share/templatetags/__init__.py
knowledge_share/templatetags/microblog.py
