Metadata-Version: 2.0
Name: django-knowledge-share
Version: 0.1.2
Summary: App to create a microblog for sharing knowledge.
Home-page: https://github.com/vintasoftware/django-knowledge-share
Author: Vinta Software
Author-email: contact@vinta.com.br
License: MIT
Keywords: django-knowledge-share
Platform: UNKNOWN
Classifier: Development Status :: 3 - Alpha
Classifier: Framework :: Django
Classifier: Framework :: Django :: 1.8
Classifier: Framework :: Django :: 1.9
Classifier: Framework :: Django :: 1.10
Classifier: Intended Audience :: Developers
Classifier: License :: OSI Approved :: BSD License
Classifier: Natural Language :: English
Classifier: Programming Language :: Python :: 2
Classifier: Programming Language :: Python :: 2.7
Classifier: Programming Language :: Python :: 3
Classifier: Programming Language :: Python :: 3.3
Classifier: Programming Language :: Python :: 3.4
Classifier: Programming Language :: Python :: 3.5
Requires-Dist: beautifulsoup4 (>=4.5.1,<4.6)
Requires-Dist: django-markdown (>=0.8.4,<0.9)
Requires-Dist: lxml (>=3.6.0,<3.7)
Requires-Dist: misaka (<2.2,>=2.0.0)
Requires-Dist: tapioca-twitter (<0.9,>=0.8.2)
